py_env_parser_light/__init__.py
py_env_parser_light/environment_controller.py
py_env_parser_light-0.1.dist-info/METADATA
py_env_parser_light-0.1.dist-info/WHEEL
py_env_parser_light-0.1.dist-info/top_level.txt
py_env_parser_light-0.1.dist-info/RECORD
