Metadata-Version: 2.1
Name: py_env_parser_light
Version: 0.1
Summary: A Simple env file parser
Home-page: https://github.com/stickoking/Python_Env_Parser
Author: Prasshant Shanmugalingam
Classifier: Programming Language :: Python :: 3
Classifier: License :: OSI Approved :: MIT License
Classifier: Operating System :: OS Independent
Requires-Python: >=3.6
